MANIFEST.in
README.md
setup.py
djangocms_styledlink/__init__.py
djangocms_styledlink/admin.py
djangocms_styledlink/cms_plugins.py
djangocms_styledlink/forms.py
djangocms_styledlink/models.py
djangocms_styledlink.egg-info/PKG-INFO
djangocms_styledlink.egg-info/SOURCES.txt
djangocms_styledlink.egg-info/dependency_links.txt
djangocms_styledlink.egg-info/not-zip-safe
djangocms_styledlink.egg-info/top_level.txt
djangocms_styledlink/migrations/0001_initial.py
djangocms_styledlink/migrations/0002_auto__add_field_styledlink_int_hash.py
djangocms_styledlink/migrations/__init__.py
djangocms_styledlink/templates/djangocms_styledlink/styled_link.html