Metadata-Version: 1.1
Name: djangocms-styledlink
Version: 0.1.4
Summary: A Universal, Styled Link Plugin for django CMS
Home-page: https://github.com/mkoistinen/djangocms-styledlink
Author: Martin Koistinen
Author-email: mkoistinen@gmail.com
License: LICENSE.txt
Download-URL: https://github.com/mkoistinen/djangocms-styledlink/tarball/0.1.1
Platform: OS Independent
Classifier: Development Status :: 5 - Production/Stable
Classifier: Environment :: Web Environment
Classifier: Framework :: Django
Classifier: Intended Audience :: Developers
Classifier: License :: OSI Approved :: BSD License
Classifier: Operating System :: OS Independent
Classifier: Programming Language :: Python
Classifier: Topic :: Communications
Classifier: Topic :: Internet :: WWW/HTTP :: Dynamic Content
Classifier: Topic :: Internet :: WWW/HTTP :: Dynamic Content :: Message Boards
Classifier: Programming Language :: Python :: 2.6
Classifier: Programming Language :: Python :: 2.7
